pyalohabotany/__init__.py
pyalohabotany/api.py
pyalohabotany/middleware.py
pyalohabotany/response.py
pyalohabotanyframework-0.0.1.dist-info/METADATA
pyalohabotanyframework-0.0.1.dist-info/WHEEL
pyalohabotanyframework-0.0.1.dist-info/top_level.txt
pyalohabotanyframework-0.0.1.dist-info/RECORD
